wtsize/__init__.py
wtsize/__main__.py
wtsize/wtsize.py
wtsize-0.1.0.dist-info/METADATA
wtsize-0.1.0.dist-info/RECORD
wtsize-0.1.0.dist-info/WHEEL
wtsize-0.1.0.dist-info/entry_points.txt
wtsize-0.1.0.dist-info/top_level.txt
