Metadata-Version: 2.1
Name: wtsize
Version: 0.1.0
Summary: WTSize let's you check the size of a remote file without downloading it.
Home-page: https://github.com/davidhamann/wtsize
Author: David Hamann
Author-email: dh@davidhamann.de
License: UNKNOWN
Platform: UNKNOWN
Classifier: Programming Language :: Python
Classifier: Programming Language :: Python :: 3.6
Classifier: License :: OSI Approved :: MIT License
Classifier: Operating System :: OS Independent
Requires-Dist: requests
Requires-Dist: docopt
